.VERSION
AUTHORS.rst
CONTRIBUTING.rst
HISTORY.rst
LICENSE
MANIFEST.in
Pipfile
Pipfile.lock
README.rst
USAGE.rst
dev-requirements.txt
requirements.txt
setup.cfg
setup.py
docs/Makefile
docs/authors.rst
docs/conf.py
docs/contributing.rst
docs/history.rst
docs/index.rst
docs/installation.rst
docs/readme.rst
docs/usage.rst
tests/test_wikiserieswillemlib.py
wikiserieswillemlib/.VERSION
wikiserieswillemlib/AUTHORS.rst
wikiserieswillemlib/CONTRIBUTING.rst
wikiserieswillemlib/HISTORY.rst
wikiserieswillemlib/LICENSE
wikiserieswillemlib/Pipfile
wikiserieswillemlib/Pipfile.lock
wikiserieswillemlib/README.rst
wikiserieswillemlib/USAGE.rst
wikiserieswillemlib/__init__.py
wikiserieswillemlib/_version.py
wikiserieswillemlib/dev-requirements.txt
wikiserieswillemlib/requirements.txt
wikiserieswillemlib/wikiserieswillemlib.py
wikiserieswillemlib/wikiserieswillemlibexceptions.py
wikiserieswillemlib.egg-info/PKG-INFO
wikiserieswillemlib.egg-info/SOURCES.txt
wikiserieswillemlib.egg-info/dependency_links.txt
wikiserieswillemlib.egg-info/not-zip-safe
wikiserieswillemlib.egg-info/requires.txt
wikiserieswillemlib.egg-info/top_level.txt