Metadata-Version: 2.1
Name: wikiserieswillemlib
Version: 0.1.0
Summary: A library for parsing Wiki series
Home-page: https://github.com/wmkuipers/wikiserieswillemlib
Author: Willem Kuipers
Author-email: willem@kuipers.co.uk
License: MIT
Keywords: wikiserieswillemlib
Classifier: Development Status :: 3 - Alpha
Classifier: Intended Audience :: Developers
Classifier: License :: OSI Approved :: MIT License
Classifier: Natural Language :: English
Classifier: Programming Language :: Python :: 3.9
License-File: LICENSE
License-File: AUTHORS.rst
